[{"city": "moscow", "download_speed": 126, "upload_speed": 67, "latency": 12.404}, {"city": "warsaw", "download_speed": 131, "upload_speed": 50, "latency": 18.01}, {"city": "berlin", "download_speed": 84, "upload_speed": 41, "latency": 23.069}, {"city": "paris", "download_speed": 116, "upload_speed": 11, "latency": 30.608}, {"city": "london", "download_speed": 168, "upload_speed": 30, "latency": 32.794}, {"city": "urumqi", "download_speed": 28, "upload_speed": 13, "latency": 66.601}, {"city": "newyork", "download_speed": 19, "upload_speed": 10, "latency": 91.949}, {"city": "ottawa", "download_speed": 19, "upload_speed": 8, "latency": 113.916}, {"city": "beijing", "download_speed": 0, "upload_speed": 0, "latency": 123.757}, {"city": "hongkong", "download_speed": 51, "upload_speed": 7, "latency": 128.344}, {"city": "osaka", "download_speed": 26, "upload_speed": 7, "latency": 128.951}, {"city": "tokyo", "download_speed": 19, "upload_speed": 7, "latency": 128.972}, {"city": "seoul", "download_speed": 0, "upload_speed": 4, "latency": 130.643}, {"city": "kampala", "download_speed": 30, "upload_speed": 6, "latency": 152.357}, {"city": "delhi", "download_speed": 17, "upload_speed": 6, "latency": 152.933}, {"city": "monterrey", "download_speed": 5, "upload_speed": 6, "latency": 153.613}, {"city": "sanfrancisco", "download_speed": 27, "upload_speed": 3, "latency": 157.973}, {"city": "yishun", "download_speed": 43, "upload_speed": 6, "latency": 167.963}, {"city": "capetown", "download_speed": 48, "upload_speed": 6, "latency": 176.214}, {"city": "shanghai", "download_speed": 0, "upload_speed": 3, "latency": 182.908}, {"city": "bangkok", "download_speed": 14, "upload_speed": 5, "latency": 188.832}, {"city": "maputo", "download_speed": 22, "upload_speed": 5, "latency": 189.494}, {"city": "honolulu", "download_speed": 0, "upload_speed": 0, "latency": 209.967}, {"city": "brasilia", "download_speed": 11, "upload_speed": 2, "latency": 213.521}, {"city": "perth", "download_speed": 10, "upload_speed": 5, "latency": 214.302}, {"city": "sydney", "download_speed": 31, "upload_speed": 4, "latency": 259.112}]